{
  "bestHomeTeamPlayers": [
    {
      "value": "7.6",
      "label": "rating",
      "player": {
        "name": "Afonso Moreira",
        "firstName": "Afonso",
        "lastName": "Moreira",
        "slug": "afonso-moreira",
        "shortName": "A. Moreira",
        "position": "F",
        "jerseyNumber": "17",
        "height": 175,
        "userCount": 4684,
        "gender": "M",
        "id": 1215906,
        "marketValueCurrency": "EUR",
        "dateOfBirthTimestamp": 1111190400,
        "proposedMarketValueRaw": {
          "value": 9200000,
          "currency": "EUR"
        },
        "fieldTranslations": {
          "nameTranslation": {
            "ar": "أ. باموند / ج. كامبوزانو فاسكيز",
            "bn": "আফনসো মোরেরা",
            "hi": "अफोंसो मोरेरा"
          },
          "shortNameTranslation": {
            "ar": "أ. فاسكيز",
            "bn": "এ. মোরেরা",
            "hi": "ए. मोरेरा"
          }
        }
      }
    },
    {
      "value": "7.6",
      "label": "rating",
      "player": {
        "name": "Malick Fofana",
        "firstName": "Malick Fofana",
        "lastName": "",
        "slug": "malick-fofana",
        "shortName": "M. Fofana",
        "position": "M",
        "jerseyNumber": "11",
        "height": 169,
        "userCount": 6558,
        "gender": "M",
        "id": 1195784,
        "marketValueCurrency": "EUR",
        "dateOfBirthTimestamp": 1112227200,
        "proposedMarketValueRaw": {
          "value": 29000000,
          "currency": "EUR"
        },
        "fieldTranslations": {
          "nameTranslation": {
            "ar": "ماليك فوفانا",
            "bn": "মালিক ফোফানা",
            "hi": "मलिक फ़ोफ़ाना"
          },
          "shortNameTranslation": {
            "ar": "م. فوفانا",
            "bn": "এম. ফোফানা",
            "hi": "एम. फ़ोफ़ाना"
          }
        }
      }
    },
    {
      "value": "6.9",
      "label": "rating",
      "player": {
        "name": "Abner Vinícius",
        "firstName": "",
        "lastName": "",
        "slug": "abner-vinicius",
        "shortName": "Abner Vinícius",
        "position": "D",
        "jerseyNumber": "16",
        "height": 181,
        "userCount": 4076,
        "gender": "M",
        "id": 973838,
        "marketValueCurrency": "EUR",
        "dateOfBirthTimestamp": 959385600,
        "proposedMarketValueRaw": {
          "value": 9200000,
          "currency": "EUR"
        },
        "fieldTranslations": {
          "nameTranslation": {
            "ar": "أبنر فينيسيوس",
            "bn": "আবনার ভিনিসিয়াস",
            "hi": "अब्नेर विनीसियस"
          },
          "shortNameTranslation": {
            "ar": "أ. فينيسيوس",
            "bn": "আবনার ভিনিসিয়াস",
            "hi": "अब्नेर विनीसियस"
          }
        }
      }
    }
  ],
  "bestAwayTeamPlayers": [
    {
      "value": "8.5",
      "label": "rating",
      "player": {
        "name": "Florian Sotoca",
        "firstName": "Florian",
        "lastName": "Sotoca",
        "slug": "florian-sotoca",
        "shortName": "F. Sotoca",
        "position": "F",
        "jerseyNumber": "7",
        "height": 187,
        "userCount": 893,
        "gender": "M",
        "id": 788921,
        "marketValueCurrency": "EUR",
        "dateOfBirthTimestamp": 656812800,
        "proposedMarketValueRaw": {
          "value": 1600000,
          "currency": "EUR"
        },
        "fieldTranslations": {
          "nameTranslation": {
            "ar": "فلوريان سوتوكا",
            "bn": "ফ্লোরিয়ান সোটোকা",
            "hi": "फ्लोरियन सोटोका"
          },
          "shortNameTranslation": {
            "ar": "ف. سوتوكا",
            "bn": "এফ. সোটোকা",
            "hi": "एफ. सोटोका"
          }
        }
      }
    },
    {
      "value": "8.4",
      "label": "rating",
      "player": {
        "name": "Wesley Saïd",
        "slug": "wesley-said",
        "shortName": "W. Saïd",
        "position": "F",
        "jerseyNumber": "22",
        "height": 171,
        "userCount": 1272,
        "gender": "M",
        "id": 227862,
        "marketValueCurrency": "EUR",
        "dateOfBirthTimestamp": 798249600,
        "proposedMarketValueRaw": {
          "value": 6300000,
          "currency": "EUR"
        },
        "fieldTranslations": {
          "nameTranslation": {
            "ar": "ويزلي سعيد",
            "bn": "ওয়েসলি সাঈদ",
            "hi": "वेस्ली सैद"
          },
          "shortNameTranslation": {
            "ar": "و. سعيد",
            "bn": "ডব্লিউ. সাঈদ",
            "hi": "डब्लू. सैद"
          }
        }
      }
    },
    {
      "value": "8.3",
      "label": "rating",
      "player": {
        "name": "Mathieu Gorgelin",
        "firstName": "Mathieu",
        "lastName": "Gorgelin",
        "slug": "mathieu-gorgelin",
        "shortName": "M. Gorgelin",
        "position": "G",
        "jerseyNumber": "16",
        "height": 187,
        "userCount": 154,
        "gender": "M",
        "id": 123226,
        "marketValueCurrency": "EUR",
        "dateOfBirthTimestamp": 649814400,
        "proposedMarketValueRaw": {
          "value": 260000,
          "currency": "EUR"
        },
        "fieldTranslations": {
          "nameTranslation": {
            "ar": "ماثيو غورغيلين",
            "bn": "ম্যাথিউ গর্জেলিন",
            "hi": "मैथ्यू गोरगेलिन"
          },
          "shortNameTranslation": {
            "ar": "م. غورغيلين",
            "bn": "এম. গর্জেলিন",
            "hi": "एम. गोरगेलिन"
          }
        }
      }
    }
  ],
  "playerOfTheMatch": {
    "value": "8.5",
    "label": "rating",
    "player": {
      "name": "Florian Sotoca",
      "firstName": "Florian",
      "lastName": "Sotoca",
      "slug": "florian-sotoca",
      "shortName": "F. Sotoca",
      "position": "F",
      "jerseyNumber": "7",
      "height": 187,
      "userCount": 893,
      "gender": "M",
      "id": 788921,
      "marketValueCurrency": "EUR",
      "dateOfBirthTimestamp": 656812800,
      "proposedMarketValueRaw": {
        "value": 1600000,
        "currency": "EUR"
      },
      "fieldTranslations": {
        "nameTranslation": {
          "ar": "فلوريان سوتوكا",
          "bn": "ফ্লোরিয়ান সোটোকা",
          "hi": "फ्लोरियन सोटोका"
        },
        "shortNameTranslation": {
          "ar": "ف. سوتوكا",
          "bn": "এফ. সোটোকা",
          "hi": "एफ. सोटोका"
        }
      }
    }
  }
}