{
  "bestHomeTeamPlayers": [
    {
      "value": "9.8",
      "label": "rating",
      "player": {
        "name": "Jan Oblak",
        "slug": "jan-oblak",
        "shortName": "J. Oblak",
        "position": "G",
        "jerseyNumber": "13",
        "height": 189,
        "userCount": 14611,
        "gender": "M",
        "sofascoreId": "oblakjan",
        "id": 69768,
        "marketValueCurrency": "EUR",
        "dateOfBirthTimestamp": 726364800,
        "proposedMarketValueRaw": {
          "value": 18100000,
          "currency": "EUR"
        },
        "fieldTranslations": {
          "nameTranslation": {
            "ar": "يان أوبلاك",
            "bn": "জন ওব্লাক",
            "hi": "जान ओबलाक"
          },
          "shortNameTranslation": {
            "ar": "ي. أوبلاك",
            "bn": "জে. ওব্লাক",
            "hi": "जे. ओबलाक"
          }
        }
      }
    },
    {
      "value": "7.7",
      "label": "rating",
      "player": {
        "name": "Robin Le Normand",
        "firstName": "Robin",
        "lastName": "Le Normand",
        "slug": "robin-le-normand",
        "shortName": "R. Le Normand",
        "position": "D",
        "jerseyNumber": "24",
        "height": 187,
        "userCount": 7188,
        "gender": "M",
        "sofascoreId": "lenormand_r",
        "id": 787751,
        "marketValueCurrency": "EUR",
        "dateOfBirthTimestamp": 847670400,
        "proposedMarketValueRaw": {
          "value": 24000000,
          "currency": "EUR"
        },
        "fieldTranslations": {
          "nameTranslation": {
            "ar": "روبن لو نورماند",
            "bn": "রবিন লে নরম্যান্ড",
            "hi": "रॉबिन ले नॉर्मंड"
          },
          "shortNameTranslation": {
            "ar": "ر. نورماند",
            "bn": "আর. লে নরম্যান্ড",
            "hi": "आर. ले"
          }
        }
      }
    },
    {
      "value": "7.6",
      "label": "rating",
      "player": {
        "name": "Antoine Griezmann",
        "slug": "antoine-griezmann",
        "shortName": "A. Griezmann",
        "position": "F",
        "jerseyNumber": "7",
        "height": 176,
        "userCount": 108428,
        "gender": "M",
        "sofascoreId": "AGriez",
        "id": 85859,
        "marketValueCurrency": "EUR",
        "dateOfBirthTimestamp": 669513600,
        "proposedMarketValueRaw": {
          "value": 9500000,
          "currency": "EUR"
        },
        "fieldTranslations": {
          "nameTranslation": {
            "ar": "أنطوان غريزمان",
            "bn": "অ্যান্টোইন গ্রিজম্যান",
            "hi": "एंटोनी ग्रीज़मैन"
          },
          "shortNameTranslation": {
            "ar": "أ. غريزمان",
            "bn": "এ. গ্রিজম্যান",
            "hi": "ए. ग्रीज़मैन"
          }
        }
      }
    }
  ],
  "bestAwayTeamPlayers": [
    {
      "value": "8.0",
      "label": "rating",
      "player": {
        "name": "Azzedine Ounahi",
        "slug": "azzedine-ounahi",
        "shortName": "A. Ounahi",
        "position": "M",
        "jerseyNumber": "18",
        "height": 182,
        "userCount": 36560,
        "gender": "M",
        "sofascoreId": "azzedine_ounahi",
        "id": 991421,
        "marketValueCurrency": "EUR",
        "dateOfBirthTimestamp": 956102400,
        "proposedMarketValueRaw": {
          "value": 10300000,
          "currency": "EUR"
        },
        "fieldTranslations": {
          "nameTranslation": {
            "ar": "عز الدين أوناحي",
            "bn": "আজেদিন ওনাহি",
            "hi": "अज़्ज़ेदीन ओउनाही"
          },
          "shortNameTranslation": {
            "ar": "ع. أوناحي",
            "bn": "এ. ওনাহি",
            "hi": "ए. ओउनाही"
          }
        }
      }
    },
    {
      "value": "7.5",
      "label": "rating",
      "player": {
        "name": "Joel Roca",
        "firstName": "",
        "lastName": "",
        "slug": "joel-roca",
        "shortName": "J. Roca",
        "position": "M",
        "jerseyNumber": "3",
        "height": 176,
        "userCount": 807,
        "gender": "M",
        "id": 1391616,
        "marketValueCurrency": "EUR",
        "dateOfBirthTimestamp": 1118102400,
        "proposedMarketValueRaw": {
          "value": 5200000,
          "currency": "EUR"
        },
        "fieldTranslations": {
          "nameTranslation": {
            "ar": "جويل روكا",
            "bn": "জোয়েল রোকা",
            "hi": "जोएल रोका"
          },
          "shortNameTranslation": {
            "ar": "ج. روكا",
            "bn": "জে. রোকা",
            "hi": "जे. रोका"
          }
        }
      }
    },
    {
      "value": "7.4",
      "label": "rating",
      "player": {
        "name": "Alejandro Francés",
        "slug": "alejandro-frances",
        "shortName": "A. Francés",
        "position": "D",
        "jerseyNumber": "16",
        "height": 180,
        "userCount": 649,
        "gender": "M",
        "id": 1002347,
        "marketValueCurrency": "EUR",
        "dateOfBirthTimestamp": 1028160000,
        "proposedMarketValueRaw": {
          "value": 2800000,
          "currency": "EUR"
        },
        "fieldTranslations": {
          "nameTranslation": {
            "ar": "أليخاندرو فرانثيس"
          },
          "shortNameTranslation": {
            "ar": "أ. فرانثيس"
          }
        }
      }
    }
  ],
  "playerOfTheMatch": {
    "value": "9.8",
    "label": "rating",
    "player": {
      "name": "Jan Oblak",
      "slug": "jan-oblak",
      "shortName": "J. Oblak",
      "position": "G",
      "jerseyNumber": "13",
      "height": 189,
      "userCount": 14611,
      "gender": "M",
      "sofascoreId": "oblakjan",
      "id": 69768,
      "marketValueCurrency": "EUR",
      "dateOfBirthTimestamp": 726364800,
      "proposedMarketValueRaw": {
        "value": 18100000,
        "currency": "EUR"
      },
      "fieldTranslations": {
        "nameTranslation": {
          "ar": "يان أوبلاك",
          "bn": "জন ওব্লাক",
          "hi": "जान ओबलाक"
        },
        "shortNameTranslation": {
          "ar": "ي. أوبلاك",
          "bn": "জে. ওব্লাক",
          "hi": "जे. ओबलाक"
        }
      }
    }
  }
}